bluprint_conf-0.1.0.dist-info/METADATA
bluprint_conf-0.1.0.dist-info/WHEEL
bluprint_conf/__init__.py
bluprint_conf/config.py
bluprint_conf-0.1.0.dist-info/RECORD
