Metadata-Version: 2.1
Name: bluprint-conf
Version: 0.1.0
Summary: YAML configuration module for Bluprint
Author-Email: igor-sb <84479009+igor-sb@users.noreply.github.com>
License: MIT
Requires-Python: >=3.11
Requires-Dist: omegaconf>=2.3.0
Requires-Dist: importlib-resources>=6.1.1
Requires-Dist: ipykernel>=6.27.1; extra == "prototyping"
Provides-Extra: prototyping
